python_client_generator/__init__.py
python_client_generator/__main__.py
python_client_generator/exceptions.py
python_client_generator/generate_apis.py
python_client_generator/generate_base_client.py
python_client_generator/generate_models.py
python_client_generator/generate_pyproject.py
python_client_generator/main.py
python_client_generator/templates/__init__.py
python_client_generator/templates/apis.py.mustache
python_client_generator/templates/base_client.py.mustache
python_client_generator/templates/models.py.mustache
python_client_generator/templates/pyproject.toml.mustache
python_client_generator/utils.py
python_client_generator-1.3.1.dist-info/LICENSE
python_client_generator-1.3.1.dist-info/METADATA
python_client_generator-1.3.1.dist-info/WHEEL
python_client_generator-1.3.1.dist-info/entry_points.txt
python_client_generator-1.3.1.dist-info/RECORD
