Metadata-Version: 2.1
Name: python-client-generator
Version: 1.3.1
Summary: Python package to generate an httpx-based client off an OpenAPI spec
Home-page: https://github.com/sennder/python-client-generator
Author: Bogdan Petre
Author-email: bogdan.petre@sennder.com
Requires-Python: >=3.8,<4.0
Classifier: Programming Language :: Python :: 3
Classifier: Programming Language :: Python :: 3.8
Classifier: Programming Language :: Python :: 3.9
Classifier: Programming Language :: Python :: 3.10
Classifier: Programming Language :: Python :: 3.11
Requires-Dist: chevron (>=0.14.0,<0.15.0)
Requires-Dist: pydantic (>=1.9.1,<2.0.0)
Requires-Dist: semver (>=3.0.0,<4.0.0)
Project-URL: Repository, https://github.com/sennder/python-client-generator
Project-URL: download, https://github.com/sennder/python-client-generator/releases
Project-URL: tracker, https://github.com/sennder/python-client-generator/issues
